google-workspace/__init__.py
google-workspace/drive/__init__.py
google-workspace/drive/drive.py
google-workspace/drive/scopes.py
google-workspace/gmail/__init__.py
google-workspace/gmail/flood_prevention.py
google-workspace/gmail/gmail.py
google-workspace/gmail/gmail_base.py
google-workspace/gmail/label.py
google-workspace/gmail/message.py
google-workspace/gmail/scopes.py
google-workspace/gmail/utils.py
google-workspace/service/__init__.py
google-workspace/service/service.py
google-workspace/service/utils.py
google-workspace/types/__init__.py
google-workspace/types/types.py
google_workspace/__init__.py
google_workspace/drive/__init__.py
google_workspace/drive/drive.py
google_workspace/drive/scopes.py
google_workspace/gmail/__init__.py
google_workspace/gmail/flood_prevention.py
google_workspace/gmail/gmail.py
google_workspace/gmail/gmail_base.py
google_workspace/gmail/handlers.py
google_workspace/gmail/helper.py
google_workspace/gmail/histories.py
google_workspace/gmail/label.py
google_workspace/gmail/message.py
google_workspace/gmail/scopes.py
google_workspace/gmail/thread.py
google_workspace/gmail/utils.py
google_workspace/service/__init__.py
google_workspace/service/service.py
google_workspace/service/utils.py
google_workspace/types/__init__.py
google_workspace/types/types.py
google_workspace-0.20.2.dist-info/LICENSE
google_workspace-0.20.2.dist-info/METADATA
google_workspace-0.20.2.dist-info/WHEEL
google_workspace-0.20.2.dist-info/top_level.txt
google_workspace-0.20.2.dist-info/RECORD
