Metadata-Version: 2.1
Name: google-workspace
Version: 0.20.2
Summary: A Python wrapper for the google workspace APIs
Home-page: https://github.com/dermasmid/google-workspace
Author: Cheskel Twersky
Author-email: twerskycheskel@gmail.com
License: MIT
Keywords: gmail gmail-api drive google-drive google-drive-api api-wrapper python3 python
Platform: UNKNOWN
Classifier: Programming Language :: Python :: 3
Classifier: License :: OSI Approved :: MIT License
Classifier: Operating System :: OS Independent
Requires-Python: >=3.6
License-File: LICENSE
Requires-Dist: google-api-python-client
Requires-Dist: google-auth-oauthlib
Requires-Dist: chardet
Requires-Dist: python-magic
Requires-Dist: trython
Requires-Dist: typing-extensions
